glud/__init__.py
glud/display.py
glud/internal.py
glud/matchers.py
glud/parsing.py
glud/predicates.py
glud/traversal.py
glud/version.py
glud-0.3.2.dist-info/DESCRIPTION.rst
glud-0.3.2.dist-info/METADATA
glud-0.3.2.dist-info/RECORD
glud-0.3.2.dist-info/WHEEL
glud-0.3.2.dist-info/metadata.json
glud-0.3.2.dist-info/top_level.txt
tests/__init__.py
tests/test_dump_ast.py
tests/test_parse.py
tests/test_traversal.py
tests/utils.py
