Metadata-Version: 2.0
Name: glud
Version: 0.3.2
Summary: Functional tools for matching nodes in the clang AST
Home-page: http://github.com/AndrewWalker/glud
Author: Andrew Walker
Author-email: walker.ab@gmail.com
License: MIT
Keywords: libclang,clang,AST
Platform: UNKNOWN
Classifier: Topic :: Software Development :: Compilers
Classifier: Development Status :: 4 - Beta
Classifier: Intended Audience :: Developers
Classifier: License :: OSI Approved :: MIT License
Classifier: Natural Language :: English
Classifier: Programming Language :: Python :: 2
Classifier: Programming Language :: Python :: 3
Classifier: Programming Language :: Python :: 2.7
Classifier: Programming Language :: Python :: 3.3
Classifier: Programming Language :: Python :: 3.4
Classifier: Programming Language :: Python :: 3.5
Classifier: Operating System :: POSIX :: Linux
Requires-Dist: asciitree
Requires-Dist: clang
